plone.formwidget.namedfile-3.1.2-py3.13-nspkg.pth
plone/formwidget/namedfile/__init__.py
plone/formwidget/namedfile/configure.zcml
plone/formwidget/namedfile/converter.py
plone/formwidget/namedfile/datamanager.py
plone/formwidget/namedfile/file_display.pt
plone/formwidget/namedfile/file_input.pt
plone/formwidget/namedfile/image.jpg
plone/formwidget/namedfile/image_display.pt
plone/formwidget/namedfile/image_input.pt
plone/formwidget/namedfile/interfaces.py
plone/formwidget/namedfile/testing.py
plone/formwidget/namedfile/tests.py
plone/formwidget/namedfile/utils.py
plone/formwidget/namedfile/validator.py
plone/formwidget/namedfile/widget.py
plone/formwidget/namedfile/widget.rst
plone_formwidget_namedfile-3.1.2.dist-info/METADATA
plone_formwidget_namedfile-3.1.2.dist-info/WHEEL
plone_formwidget_namedfile-3.1.2.dist-info/namespace_packages.txt
plone_formwidget_namedfile-3.1.2.dist-info/top_level.txt
plone_formwidget_namedfile-3.1.2.dist-info/RECORD
