Metadata-Version: 2.4
Name: plone.formwidget.namedfile
Version: 3.1.2
Summary: Image widget for z3c.form and Plone
Home-page: https://pypi.org/project/plone.formwidget.namedfile
Author: Martin Aspeli
Author-email: optilude@gmail.com
License: GPL
Keywords: plone image widget z3c.form
Classifier: Development Status :: 5 - Production/Stable
Classifier: Framework :: Plone
Classifier: Framework :: Plone :: 6.0
Classifier: License :: OSI Approved :: GNU General Public License (GPL)
Classifier: Programming Language :: Python
Classifier: Programming Language :: Python :: 3.8
Classifier: Programming Language :: Python :: 3.9
Classifier: Programming Language :: Python :: 3.10
Classifier: Programming Language :: Python :: 3.11
Classifier: Topic :: Software Development :: Libraries :: Python Modules
Requires-Python: >=3.8
Requires-Dist: setuptools
Requires-Dist: plone.base
Requires-Dist: plone.namedfile>=6.3.0
Requires-Dist: Products.MimetypesRegistry
Requires-Dist: plone.registry
Requires-Dist: z3c.form
Requires-Dist: Zope
Provides-Extra: test
Requires-Dist: Pillow; extra == "test"
Requires-Dist: plone.app.testing; extra == "test"
Requires-Dist: plone.scale; extra == "test"
Requires-Dist: plone.testing; extra == "test"
Requires-Dist: zope.pagetemplate; extra == "test"
Dynamic: author
Dynamic: author-email
Dynamic: classifier
Dynamic: description
Dynamic: home-page
Dynamic: keywords
Dynamic: license
Dynamic: provides-extra
Dynamic: requires-dist
Dynamic: requires-python
Dynamic: summary
